lux/__init__.py
lux/client.py
lux/command.py
lux/config.py
lux/contexter.py
lux/dutils.py
lux/zutils.py
zenlux/__init__.py
zenlux/client.py
zenlux/command.py
zenlux/config.py
zenlux/contexter.py
zenlux/dutils.py
zenlux/zutils.py
zenlux-0.0.2.dist-info/METADATA
zenlux-0.0.2.dist-info/WHEEL
zenlux-0.0.2.dist-info/top_level.txt
zenlux-0.0.2.dist-info/RECORD
