Metadata-Version: 2.1
Name: zenlux
Version: 0.0.2
Summary: A microframework
Home-page: https://github.com/Zenith00/lux
Author: Zenith00
Author-email: Zenith00dev@gmail.com
License: UNKNOWN
Platform: UNKNOWN
Classifier: Programming Language :: Python :: 3
Requires-Dist: discord
